spnego/__init__.py
spnego/__main__.py
spnego/_asn1.py
spnego/_context.py
spnego/_credential.py
spnego/_credssp.py
spnego/_credssp_structures.py
spnego/_gss.py
spnego/_kerberos.py
spnego/_negotiate.py
spnego/_ntlm.py
spnego/_spnego.py
spnego/_sspi.py
spnego/_text.py
spnego/_tls_struct.py
spnego/_version.py
spnego/auth.py
spnego/channel_bindings.py
spnego/exceptions.py
spnego/gss.py
spnego/iov.py
spnego/negotiate.py
spnego/ntlm.py
spnego/py.typed
spnego/sspi.py
spnego/tls.py
spnego/_ntlm_raw/__init__.py
spnego/_ntlm_raw/crypto.py
spnego/_ntlm_raw/des.py
spnego/_ntlm_raw/md4.py
spnego/_ntlm_raw/messages.py
spnego/_ntlm_raw/security.py
pyspnego-0.11.1.dist-info/LICENSE
pyspnego-0.11.1.dist-info/METADATA
pyspnego-0.11.1.dist-info/WHEEL
pyspnego-0.11.1.dist-info/entry_points.txt
pyspnego-0.11.1.dist-info/top_level.txt
pyspnego-0.11.1.dist-info/RECORD
