Metadata-Version: 2.1
Name: pyspnego
Version: 0.11.1
Summary: Windows Negotiate Authentication Client and Server
Author-email: Jordan Borean <jborean93@gmail.com>
License: MIT License
Project-URL: homepage, https://github.com/jborean93/pyspnego
Keywords: windows,spnego,negotiate,ntlm,kerberos,sspi,gssapi,auth
Classifier: Development Status :: 4 - Beta
Classifier: License :: OSI Approved :: MIT License
Classifier: Programming Language :: Python :: 3
Classifier: Programming Language :: Python :: 3.8
Classifier: Programming Language :: Python :: 3.9
Classifier: Programming Language :: Python :: 3.10
Classifier: Programming Language :: Python :: 3.11
Classifier: Programming Language :: Python :: 3.12
Requires-Python: >=3.8
License-File: LICENSE
Requires-Dist: cryptography
Requires-Dist: sspilib>=0.1.0; sys_platform == "win32"
Provides-Extra: kerberos
Requires-Dist: gssapi>=1.6.0; sys_platform != "win32" and extra == "kerberos"
Requires-Dist: krb5>=0.3.0; sys_platform != "win32" and extra == "kerberos"
Provides-Extra: yaml
Requires-Dist: ruamel.yaml; extra == "yaml"
